{
  "unversionedId": "Integrate- 3rd Party Applications/tableau",
  "id": "Integrate- 3rd Party Applications/tableau",
  "title": "Tableau",
  "description": "Install the Avatica JDBC driver",
  "source": "@site/docs/Integrate- 3rd Party Applications/tableau.md",
  "sourceDirName": "Integrate- 3rd Party Applications",
  "slug": "/Integrate- 3rd Party Applications/tableau",
  "permalink": "/Integrate- 3rd Party Applications/tableau",
  "draft": false,
  "editUrl": "https://github.com/rilldata/rill-developer/blob/main/docs-enterprise/docs/Integrate- 3rd Party Applications/tableau.md",
  "tags": [],
  "version": "current",
  "frontMatter": {
    "title": "Tableau",
    "slug": "tableau",
    "excerpt": "Integrating Rill with Tableau",
    "hidden": false,
    "createdAt": "2020-09-29T23:44:04.538Z",
    "updatedAt": "2021-09-21T18:51:45.545Z"
  }
}