{
  "unversionedId": "Analyze- Explore Dashboards/explore-admin/admin-security",
  "id": "Analyze- Explore Dashboards/explore-admin/admin-security",
  "title": "Permissions & Security Policies",
  "description": "[block:api-header]",
  "source": "@site/docs/Analyze- Explore Dashboards/explore-admin/admin-security.md",
  "sourceDirName": "Analyze- Explore Dashboards/explore-admin",
  "slug": "/Analyze- Explore Dashboards/explore-admin/admin-security",
  "permalink": "/Analyze- Explore Dashboards/explore-admin/admin-security",
  "draft": false,
  "editUrl": "https://github.com/rilldata/rill-developer/blob/main/docs-enterprise/docs/Analyze- Explore Dashboards/explore-admin/admin-security.md",
  "tags": [],
  "version": "current",
  "frontMatter": {
    "title": "Permissions & Security Policies",
    "slug": "admin-security",
    "excerpt": "How to manage access and log-in to Explore",
    "hidden": false,
    "createdAt": "2021-08-11T18:42:21.908Z",
    "updatedAt": "2022-07-13T07:13:03.575Z"
  }
}